reader/__init__.py
reader/__main__.py
reader/config.toml
reader/feed.py
reader/viewer.py
mugendi_realpython_reader-1.2.0.dist-info/LICENSE
mugendi_realpython_reader-1.2.0.dist-info/METADATA
mugendi_realpython_reader-1.2.0.dist-info/WHEEL
mugendi_realpython_reader-1.2.0.dist-info/entry_points.txt
mugendi_realpython_reader-1.2.0.dist-info/top_level.txt
mugendi_realpython_reader-1.2.0.dist-info/RECORD
