Metadata-Version: 2.1
Name: mugendi-realpython-reader
Version: 1.2.0
Summary: Read the latest Real Python tutorials
Author-email: Real Python <info@realpython.com>
License: MIT License
Project-URL: repository, https://github.com/realpython/reader
Project-URL: documentation, https://realpython.com/pypi-publish-python-package/
Keywords: feed,reader,tutorial
Classifier: License :: OSI Approved :: MIT License
Classifier: Programming Language :: Python
Classifier: Programming Language :: Python :: 3
Requires-Python: >=3.7
License-File: LICENSE
Requires-Dist: feedparser
Requires-Dist: html2text
Requires-Dist: tomli ; python_version < "3.11"
Provides-Extra: build
Requires-Dist: build ; extra == 'build'
Requires-Dist: twine ; extra == 'build'
Provides-Extra: dev
Requires-Dist: black ; extra == 'dev'
Requires-Dist: bumpver ; extra == 'dev'
Requires-Dist: isort ; extra == 'dev'
Requires-Dist: mypy ; extra == 'dev'
Requires-Dist: pytest ; extra == 'dev'
